{
    "usuarios": [
        {
            "_nome": "pedro",
            "_email": "pedro@gmail.com",
            "_senha_hash": "a665a45920422f9d417e4867efdc4fb8a04a1f3fff1fa07e998e86f7f7a27ae3"
        },
        {
            "_nome": "clara",
            "_email": "clara@gmail.com",
            "_senha_hash": "a665a45920422f9d417e4867efdc4fb8a04a1f3fff1fa07e998e86f7f7a27ae3"
        }
    ],
    "caronas": [
        {
            "origem": "Guará",
            "data": "20/05",
            "horario": "12:00",
            "passageiros": [
                "clara@gmail.com"
            ]
        }
    ]
}